Metadata-Version: 2.1
Name: XPlaneApi
Version: 0.0.6
Summary: API Python Client for C++ Xplane Server
Home-page: https://github.com/Pietracoops/XPlane_Python_Client
Author: Massimo Pietracupa
Author-email: Massimo.Pietracupa@hotmail.com
License: MIT
Keywords: XPlane API
Platform: UNKNOWN
Classifier: Development Status :: 5 - Production/Stable
Classifier: Intended Audience :: Developers
Classifier: Intended Audience :: Science/Research
Classifier: License :: OSI Approved :: MIT License
Classifier: Operating System :: Microsoft :: Windows
Classifier: Programming Language :: Python :: 3.7
Classifier: Programming Language :: Python :: 3.8
Classifier: Programming Language :: Python :: 3.9
Requires-Python: >=3.7
